zylo/__init__.py
zylo/cli.py
zylo/static/docs/404.html
zylo/static/docs/favicon.ico
zylo/static/docs/file.svg
zylo/static/docs/globe.svg
zylo/static/docs/index.html
zylo/static/docs/index.txt
zylo/static/docs/next.svg
zylo/static/docs/vercel.svg
zylo/static/docs/window.svg
zylo/static/docs/404/index.html
zylo/static/docs/_next/static/4oCcYRRW15XB_QUNnP8MW/_buildManifest.js
zylo/static/docs/_next/static/4oCcYRRW15XB_QUNnP8MW/_ssgManifest.js
zylo/static/docs/_next/static/chunks/4bd1b696-67ee12fb04071d3b.js
zylo/static/docs/_next/static/chunks/63-53d41cfacc2ecc15.js
zylo/static/docs/_next/static/chunks/684-3df42d032e8cc262.js
zylo/static/docs/_next/static/chunks/framework-f593a28cde54158e.js
zylo/static/docs/_next/static/chunks/main-2ee96960890d74e9.js
zylo/static/docs/_next/static/chunks/main-app-b08cc102112eabce.js
zylo/static/docs/_next/static/chunks/polyfills-42372ed130431b0a.js
zylo/static/docs/_next/static/chunks/webpack-4fb25687bffee557.js
zylo/static/docs/_next/static/chunks/app/layout-4818e47eeb2c3b06.js
zylo/static/docs/_next/static/chunks/app/page-5e78e596a46f6b3f.js
zylo/static/docs/_next/static/chunks/app/_not-found/page-f08302ee705a96b1.js
zylo/static/docs/_next/static/chunks/pages/_app-da15c11dea942c36.js
zylo/static/docs/_next/static/chunks/pages/_error-cc3f077a18ea1793.js
zylo/static/docs/_next/static/css/a76417de8aab7012.css
zylo/static/docs/_next/static/media/569ce4b8f30dc480-s.p.woff2
zylo/static/docs/_next/static/media/747892c23ea88013-s.woff2
zylo/static/docs/_next/static/media/8d697b304b401681-s.woff2
zylo/static/docs/_next/static/media/93f479601ee12b01-s.p.woff2
zylo/static/docs/_next/static/media/9610d9e46709d722-s.woff2
zylo/static/docs/_next/static/media/ba015fad6dcf6784-s.woff2
zylosystems_zylo-0.1.4.dist-info/METADATA
zylosystems_zylo-0.1.4.dist-info/WHEEL
zylosystems_zylo-0.1.4.dist-info/entry_points.txt
zylosystems_zylo-0.1.4.dist-info/top_level.txt
zylosystems_zylo-0.1.4.dist-info/RECORD
