Metadata-Version: 2.4
Name: zylosystems-zylo
Version: 0.1.4
Requires-Dist: Flask
Dynamic: requires-dist
